helloasso_api_wrapper/__about__.py
helloasso_api_wrapper/__init__.py
helloasso_api_wrapper/exceptions.py
helloasso_api_wrapper/ha_apiv5_extension.py
helloasso_api_wrapper/py.typed
helloasso_api_wrapper/clients/__init__.py
helloasso_api_wrapper/clients/checkout_intents_management.py
helloasso_api_wrapper/clients/directory.py
helloasso_api_wrapper/clients/forms.py
helloasso_api_wrapper/clients/generic_client.py
helloasso_api_wrapper/clients/orders_items.py
helloasso_api_wrapper/clients/organization_visualisation.py
helloasso_api_wrapper/clients/users.py
helloasso_api_wrapper/models/__init__.py
helloasso_api_wrapper/models/account.py
helloasso_api_wrapper/models/api_notifications.py
helloasso_api_wrapper/models/carts.py
helloasso_api_wrapper/models/clients.py
helloasso_api_wrapper/models/common.py
helloasso_api_wrapper/models/directory.py
helloasso_api_wrapper/models/enums.py
helloasso_api_wrapper/models/forms.py
helloasso_api_wrapper/models/organization.py
helloasso_api_wrapper/models/partners.py
helloasso_api_wrapper/models/payment.py
helloasso_api_wrapper/models/shared.py
helloasso_api_wrapper/models/statistics.py
helloasso_api_wrapper/models/tags.py
helloasso_api_wrapper/models/results_with_pagination_model/__init__.py
helloasso_api_wrapper/models/results_with_pagination_model/directory.py
helloasso_api_wrapper/models/results_with_pagination_model/forms.py
helloasso_api_wrapper/models/results_with_pagination_model/payment.py
helloasso_api_wrapper/models/results_with_pagination_model/statistics.py
helloassoapiwrapper-1.0.0.dist-info/METADATA
helloassoapiwrapper-1.0.0.dist-info/WHEEL
helloassoapiwrapper-1.0.0.dist-info/licenses/LICENSE
helloassoapiwrapper-1.0.0.dist-info/RECORD
