Metadata-Version: 2.3
Name: HelloAssoAPIWrapper
Version: 1.0.0
Summary: Python wrapper for Helloasso APIV5
Project-URL: Source, https://github.com/aeecleclair/HelloAssoAPIWrapper
Author: AEECL ECLAIR
License-Expression: MIT
License-File: LICENSE
Classifier: Framework :: Pydantic
Classifier: Framework :: Pydantic :: 2
Classifier: Programming Language :: Python
Classifier: Programming Language :: Python :: 3.8
Classifier: Programming Language :: Python :: 3.9
Classifier: Programming Language :: Python :: 3.10
Classifier: Programming Language :: Python :: 3.11
Classifier: Programming Language :: Python :: 3.12
Requires-Python: >=3.8
Requires-Dist: helloasso-apiv5==1.0.0
Requires-Dist: pydantic>=2.5
